easySED/SED.py
easySED/__init__.py
easySED/test.py
easySED-0.2.dist-info/LICENSE
easySED-0.2.dist-info/METADATA
easySED-0.2.dist-info/WHEEL
easySED-0.2.dist-info/top_level.txt
easySED-0.2.dist-info/RECORD
