Metadata-Version: 2.1
Name: easySED
Version: 0.2
Summary: This module to used to add military level encryption system to your project , encrypt strings , files , directories etc
Home-page: https://github.com/harshnative/easy-secure-encryptor-decryptor-module_python
Author: Harsh Native
Author-email: Harshnative@gmail.com
License: UNKNOWN
Platform: UNKNOWN
Classifier: Programming Language :: Python :: 3
Classifier: License :: OSI Approved :: MIT License
Classifier: Operating System :: OS Independent
Requires-Python: >=3.6
Requires-Dist: onetimepad
Requires-Dist: cryptography
